utboxgen_py/__init__.py
utboxgen_py/generator.py
utboxgen_py/assets/utbox_base.png
utboxgen_py/assets/utbox_font_cyr.otf
utboxgen_py-0.1.1b2.dist-info/LICENSE
utboxgen_py-0.1.1b2.dist-info/METADATA
utboxgen_py-0.1.1b2.dist-info/WHEEL
utboxgen_py-0.1.1b2.dist-info/top_level.txt
utboxgen_py-0.1.1b2.dist-info/RECORD
