Metadata-Version: 2.1
Name: utboxgen-py
Version: 0.1.1b2
Summary: A Python library for generating Undertale-styled textbox images
Author-email: A1Asriel <27139654+A1Asriel@users.noreply.github.com>
Project-URL: Homepage, https://github.com/A1Asriel/utboxgen-py
Project-URL: Issues, https://github.com/A1Asriel/utboxgen-py/issues
Classifier: Programming Language :: Python :: 3
Classifier: Programming Language :: Python :: 3.8
Classifier: License :: OSI Approved :: MIT License
Classifier: Operating System :: OS Independent
Requires-Python: >=3.8
License-File: LICENSE
Requires-Dist: Pillow <11.0.0,>=10.2.0
